MANIFEST.in
README.rst
setup.cfg
setup.py
boxr/__init__.py
boxr/tests.py
boxr.egg-info/PKG-INFO
boxr.egg-info/SOURCES.txt
boxr.egg-info/dependency_links.txt
boxr.egg-info/requires.txt
boxr.egg-info/top_level.txt