Metadata-Version: 1.1
Name: boxr
Version: 1.0.1
Summary: An Open Exchange Rate Client
Home-page: https://github.com/getmyboat/boxr
Author: GetMyBoat, LLC
Author-email: alex@getmyboat.com
License: UNKNOWN
Keywords: foreign exchange rates
Platform: UNKNOWN
Classifier: Development Status :: 3 - Alpha
Classifier: Intended Audience :: Developers
Classifier: License :: OSI Approved :: MIT License
Classifier: Programming Language :: Python :: 3
Classifier: Programming Language :: Python :: 3.4
Classifier: Programming Language :: Python :: 3.5
Classifier: Programming Language :: Python :: 3.6
